omicimage/__init__.py
omicimage/build_rgba_methylation.py
omicimage/build_rgba_nomethylation.py
omicimage/cli.py
omicimage/image_encoder.py
omicimage/methylation_loader.py
omicimage/sam_parser.py
omicimage/shared.py
omicimage/utils.py
omicimage-0.1.0.dist-info/licenses/LICENSE
omicimage-0.1.0.dist-info/METADATA
omicimage-0.1.0.dist-info/WHEEL
omicimage-0.1.0.dist-info/entry_points.txt
omicimage-0.1.0.dist-info/top_level.txt
omicimage-0.1.0.dist-info/RECORD
