Metadata-Version: 2.4
Name: omicimage
Version: 0.1.0
Summary: Convert SAM alignments (± CpG methylation) into RGBA images.
Author-email: Gabriel Abraham <ga496@cam.ac.uk>
License: MIT License
Project-URL: Homepage, https://example.com
Project-URL: Repository, https://example.com/repo
Project-URL: Issues, https://example.com/repo/issues
Keywords: bioinformatics,sam,rgba,genomics,methylation
Classifier: Programming Language :: Python :: 3
Classifier: License :: OSI Approved :: MIT License
Classifier: Operating System :: OS Independent
Classifier: Topic :: Scientific/Engineering :: Bio-Informatics
Requires-Python: >=3.9
License-File: LICENSE
Requires-Dist: numpy>=1.20
Requires-Dist: pillow>=9.0
Requires-Dist: pysam>=0.22
Requires-Dist: tqdm>=4.0
Dynamic: license-file
